state_of_things/__init__.py
state_of_things/observers.py
state_of_things/state_of_things.py
state_of_things-0.0.3.dist-info/licenses/LICENSE
state_of_things-0.0.3.dist-info/METADATA
state_of_things-0.0.3.dist-info/WHEEL
state_of_things-0.0.3.dist-info/top_level.txt
state_of_things-0.0.3.dist-info/RECORD
