Metadata-Version: 2.4
Name: state-of-things
Version: 0.0.3
Summary: State of Things python library to organize complex state machines
Author-email: Mindwidgets <aaron@mindwidgets.com>
License: MIT
Project-URL: Homepage, https://github.com/mindwidgets/state-of-things
Keywords: circuitpython,micropython
Classifier: Intended Audience :: Developers
Classifier: Topic :: Software Development :: Libraries
Classifier: Topic :: Software Development :: Embedded Systems
Classifier: License :: OSI Approved :: MIT License
Classifier: Programming Language :: Python :: 3
License-File: LICENSE
Provides-Extra: optional
Requires-Dist: tox; extra == "optional"
Dynamic: license-file
